{
  "parent": "minecraft:recipes/root",
  "criteria": {
    "has_ore": {
      "conditions": {
        "items": [
          {
            "items": [
              "chrispymod:boron_ore"
            ]
          }
        ]
      },
      "trigger": "minecraft:inventory_changed"
    },
    "has_the_recipe": {
      "conditions": {
        "recipe": "minecraft:boron_ingot_from_blasting_boron_ore"
      },
      "trigger": "minecraft:recipe_unlocked"
    }
  },
  "requirements": [
    [
      "has_ore",
      "has_the_recipe"
    ]
  ],
  "rewards": {
    "recipes": [
      "minecraft:boron_ingot_from_blasting_boron_ore"
    ]
  }
}