{
  "type": "minecraft:block",
  "pools": [
    {
      "bonus_rolls": 0.0,
      "entries": [
        {
          "type": "minecraft:alternatives",
          "children": [
            {
              "type": "minecraft:item",
              "conditions": [
                {
                  "block": "chrispymod:dewberry_bush",
                  "condition": "minecraft:block_state_property",
                  "properties": {
                    "age": "3"
                  }
                }
              ],
              "functions": [
                {
                  "add": false,
                  "count": {
                    "type": "minecraft:uniform",
                    "max": 2.0,
                    "min": 1.0
                  },
                  "function": "minecraft:set_count"
                },
                {
                  "enchantment": "minecraft:fortune",
                  "formula": "minecraft:uniform_bonus_count",
                  "function": "minecraft:apply_bonus",
                  "parameters": {
                    "bonusMultiplier": 1
                  }
                },
                {
                  "function": "minecraft:explosion_decay"
                }
              ],
              "name": "chrispymod:dewberry"
            },
            {
              "type": "minecraft:item",
              "conditions": [
                {
                  "block": "chrispymod:dewberry_bush",
                  "condition": "minecraft:block_state_property",
                  "properties": {
                    "age": "2"
                  }
                }
              ],
              "functions": [
                {
                  "add": false,
                  "count": {
                    "type": "minecraft:uniform",
                    "max": 1.0,
                    "min": 1.0
                  },
                  "function": "minecraft:set_count"
                },
                {
                  "enchantment": "minecraft:fortune",
                  "formula": "minecraft:uniform_bonus_count",
                  "function": "minecraft:apply_bonus",
                  "parameters": {
                    "bonusMultiplier": 1
                  }
                },
                {
                  "function": "minecraft:explosion_decay"
                }
              ],
              "name": "chrispymod:dewberry"
            }
          ]
        }
      ],
      "name": "chrispymod:blocks/dewberry_bush",
      "rolls": 1.0
    }
  ]
}